LICENSE
MANIFEST.in
README.md
requirements-dev.txt
requirements.txt
setup.py
ibm_cos_sdk_config/__init__.py
ibm_cos_sdk_config/common.py
ibm_cos_sdk_config/resource_configuration_v1.py
ibm_cos_sdk_config/version.py
ibm_cos_sdk_config.egg-info/PKG-INFO
ibm_cos_sdk_config.egg-info/SOURCES.txt
ibm_cos_sdk_config.egg-info/dependency_links.txt
ibm_cos_sdk_config.egg-info/requires.txt
ibm_cos_sdk_config.egg-info/top_level.txt
ibm_cos_sdk_config.egg-info/zip-safe