Metadata-Version: 2.1
Name: ibm-cos-sdk-config
Version: 2.0.3
Summary: IBM COS Resource Configuration SDK for Python
Home-page: https://github.com/IBM/ibm-cos-sdk-python-config
Author: IBM
Author-email: cossdk@us.ibm.com
License: Apache 2.0
Keywords: ibm_cos_sdk_config
Platform: UNKNOWN
Classifier: Programming Language :: Python
Classifier: Programming Language :: Python :: 3
Classifier: Programming Language :: Python :: 3.7
Classifier: Programming Language :: Python :: 3.8
Classifier: Programming Language :: Python :: 3.9
Classifier: Programming Language :: Python :: 3.10
Classifier: Programming Language :: Python :: 3.11
Classifier: Development Status :: 5 - Production/Stable
Classifier: Intended Audience :: Developers
Classifier: License :: OSI Approved :: Apache Software License
Classifier: Operating System :: OS Independent
Classifier: Topic :: Software Development :: Libraries :: Python Modules
Classifier: Topic :: Software Development :: Libraries :: Application Frameworks
License-File: LICENSE
